[
  {
    "id": "user_001",
    "followers": 120,
    "following": 80,
    "friends": [
      {
        "id": "user_002",
        "followers": 95,
        "following": 110,
        "friends": []
      },
      {
        "id": "user_003",
        "followers": 300,
        "following": 150,
        "friends": []
      }
    ]
  },
  {
    "id": "user_004",
    "followers": 45,
    "following": 60,
    "friends": [
      {
        "id": "user_005",
        "followers": 210,
        "following": 90,
        "friends": []
      }
    ]
  },
  {
    "id": "user_006",
    "followers": 500,
    "following": 200,
    "friends": []
  },
  {
    "id": "user_007",
    "followers": 15,
    "following": 25,
    "friends": [
      {
        "id": "user_008",
        "followers": 70,
        "following": 40,
        "friends": []
      },
      {
        "id": "user_009",
        "followers": 130,
        "following": 160,
        "friends": []
      }
    ]
  },
  {
    "id": "user_010",
    "followers": 1000,
    "following": 300,
    "friends": [
      {
        "id": "user_011",
        "followers": 620,
        "following": 410,
        "friends": []
      }
    ]
  }
]
